alchemyjsonschema/__init__.py
alchemyjsonschema/debug.py
alchemyjsonschema/dictify.py
alchemyjsonschema/mapping.py
alchemyjsonschema/parser.py
alchemyjsonschema/command/__init__.py
alchemyjsonschema/command/_transformer.py
alchemyjsonschema/command/driver.py
alchemyjsonschema/command/main.py
alchemyjsonschema/custom/__init__.py
alchemyjsonschema/custom/format.py
alchemyjsonschema/custom/validator.py
alchemyjsonschema-0.8.0.dist-info/LICENSE
alchemyjsonschema-0.8.0.dist-info/METADATA
alchemyjsonschema-0.8.0.dist-info/WHEEL
alchemyjsonschema-0.8.0.dist-info/entry_points.txt
alchemyjsonschema-0.8.0.dist-info/top_level.txt
alchemyjsonschema-0.8.0.dist-info/RECORD
