Metadata-Version: 2.1
Name: alchemyjsonschema
Version: 0.8.0
Summary: A package for generating json-schema models from sqlalchemy models.
Home-page: https://github.com/podhmo/alchemyjsonschema
Author: podhmo
Author-email: 
License: mit
Keywords: alchemyjsonschema sqlalchemy jsonschema schema-generation
Platform: UNKNOWN
Classifier: Programming Language :: Python
Classifier: Programming Language :: Python :: Implementation :: CPython
License-File: LICENSE
Requires-Dist: dictknife (>=0.7.2)
Requires-Dist: isodate
Requires-Dist: jsonschema
Requires-Dist: magicalimport
Requires-Dist: pytz
Requires-Dist: sqlalchemy
Requires-Dist: strict-rfc3339
Provides-Extra: docs
Provides-Extra: testing
Requires-Dist: pytest ; extra == 'testing'
Requires-Dist: webob ; extra == 'testing'
